{
  "Routes": [
    {
      "DownstreamPathTemplate": "/accounts/register",
      "DownstreamScheme": "https",
      "DownstreamHostAndPorts": [
        {
          "Host": "localhost",
          "Port": 5003
        }
      ],
      "UpstreamPathTemplate": "/accounts/register",
      "UpstreamHttpMethod": [ "Post" ],
      "AuthenticationOptions": {
        "AllowedScopes": []
      },
      "SwaggerKey": "identity"
    },
    {
      "DownstreamPathTemplate": "/accounts/editroles",
      "DownstreamScheme": "https",
      "DownstreamHostAndPorts": [
        {
          "Host": "localhost",
          "Port": 5003
        }
      ],
      "UpstreamPathTemplate": "/accounts/editroles",
      "UpstreamHttpMethod": [ "Put" ],
      "AuthenticationOptions": {
        "AllowedScopes": []
      },
      "SwaggerKey": "identity"
    },
    {
      "DownstreamPathTemplate": "/accounts/editclaims",
      "DownstreamScheme": "https",
      "DownstreamHostAndPorts": [
        {
          "Host": "localhost",
          "Port": 5003
        }
      ],
      "UpstreamPathTemplate": "/accounts/editclaims",
      "UpstreamHttpMethod": [ "Put" ],
      "AuthenticationOptions": {
        "AllowedScopes": []
      },
      "SwaggerKey": "identity"
    },
    {
      "DownstreamPathTemplate": "/accounts/getuser/{username}",
      "DownstreamScheme": "https",
      "DownstreamHostAndPorts": [
        {
          "Host": "localhost",
          "Port": 5003
        }
      ],
      "UpstreamPathTemplate": "/accounts/getuser/{username}",
      "UpstreamHttpMethod": [ "Get" ],
      "AuthenticationOptions": {
        "AllowedScopes": []
      },
      "SwaggerKey": "identity"
    },
    {
      "DownstreamPathTemplate": "/accounts/getallusers",
      "DownstreamScheme": "https",
      "DownstreamHostAndPorts": [
        {
          "Host": "localhost",
          "Port": 5003
        }
      ],
      "UpstreamPathTemplate": "/accounts/getallusers",
      "UpstreamHttpMethod": [ "Get" ],
      "AuthenticationOptions": {
        "AllowedScopes": []
      },
      "SwaggerKey": "identity"
    },
    {
      "DownstreamPathTemplate": "/accounts/removeuser",
      "DownstreamScheme": "https",
      "DownstreamHostAndPorts": [
        {
          "Host": "localhost",
          "Port": 5003
        }
      ],
      "UpstreamPathTemplate": "/accounts/removeuser",
      "UpstreamHttpMethod": [ "Delete" ],
      "AuthenticationOptions": {
        "AllowedScopes": []
      },
      "SwaggerKey": "identity"
    },
    {
      "DownstreamPathTemplate": "/roles/create",
      "DownstreamScheme": "https",
      "DownstreamHostAndPorts": [
        {
          "Host": "localhost",
          "Port": 5003
        }
      ],
      "UpstreamPathTemplate": "/roles/create",
      "UpstreamHttpMethod": [ "Post" ],
      "AuthenticationOptions": {
        "AllowedScopes": []
      },
      "SwaggerKey": "identity"
    },
    {
      "DownstreamPathTemplate": "/roles/edit",
      "DownstreamScheme": "https",
      "DownstreamHostAndPorts": [
        {
          "Host": "localhost",
          "Port": 5003
        }
      ],
      "UpstreamPathTemplate": "/roles/edit",
      "UpstreamHttpMethod": [ "Put" ],
      "AuthenticationOptions": {
        "AllowedScopes": []
      },
      "SwaggerKey": "identity"
    },
    {
      "DownstreamPathTemplate": "/roles/editclaims",
      "DownstreamScheme": "https",
      "DownstreamHostAndPorts": [
        {
          "Host": "localhost",
          "Port": 5003
        }
      ],
      "UpstreamPathTemplate": "/roles/editclaims",
      "UpstreamHttpMethod": [ "Put" ],
      "AuthenticationOptions": {
        "AllowedScopes": []
      },
      "SwaggerKey": "identity"
    },
    {
      "DownstreamPathTemplate": "/roles/delete",
      "DownstreamScheme": "https",
      "DownstreamHostAndPorts": [
        {
          "Host": "localhost",
          "Port": 5003
        }
      ],
      "UpstreamPathTemplate": "/roles/delete",
      "UpstreamHttpMethod": [ "Delete" ],
      "AuthenticationOptions": {
        "AllowedScopes": []
      },
      "SwaggerKey": "identity"
    },
    {
      "DownstreamPathTemplate": "/roles/get",
      "DownstreamScheme": "https",
      "DownstreamHostAndPorts": [
        {
          "Host": "localhost",
          "Port": 5003
        }
      ],
      "UpstreamPathTemplate": "/roles/get",
      "UpstreamHttpMethod": [ "Get" ],
      "AuthenticationOptions": {
        "AllowedScopes": []
      },
      "SwaggerKey": "identity"
    },
    {
      "DownstreamPathTemplate": "/token",
      "DownstreamScheme": "https",
      "DownstreamHostAndPorts": [
        {
          "Host": "localhost",
          "Port": 5003
        }
      ],
      "UpstreamPathTemplate": "/token",
      "UpstreamHttpMethod": [ "Post" ],
      "AuthenticationOptions": {
        "AllowedScopes": []
      },
      "SwaggerKey": "identity"
    }
  ]
}
